Metadata-Version: 2.1
Name: pypos3dv
Version: 0.6.1
Summary: Wavefront files simple 3D viewer (OpenGL GLFW based)
Home-page: https://sourceforge.net/projects/pojamas
Author: Olivier Dufailly
Author-email: dufgrinder@laposte.net
License: UNKNOWN
Platform: UNKNOWN
Classifier: Development Status :: 4 - Beta
Classifier: Programming Language :: Python :: 3
Classifier: License :: OSI Approved :: BSD License
Classifier: Operating System :: OS Independent
Requires-Python: >=3.6
